{
	"categories": [
		"tabs"
	],
	"description": {
		"en-US": "# copy-as-markdown-link\nFirefox Extension to copy the current tab's URL and title as a Markdown/Jira/HTML link to the clipboard.\nFor example, suppose your active tab is <https://bugzilla.kernel.org/show_bug.cgi?id=220522>.\nTrigger the extension action either by clicking the ![extension](https://raw.githubusercontent.com/JayBeeDe/firefox_extensions/refs/heads/main/caml/icons/icon48.png) icon in the Firefox toolbar or by using the extension shortcut configured near \"Copy the current tab's URL and title as Markdown link\" (default is `Ctrl+Alt+M`).The title of the page is \"220522 – iwlwifi: Wi-Fi 6 AX201 160MHz missing ucode firmware files\"\nSo the markdown link copied to your clipboard is:\n```markdown\n[220522 – iwlwifi: Wi-Fi 6 AX201 160MHz missing ucode firmware files](https://bugzilla.kernel.org/show_bug.cgi?id=220522)\n```\n"
	},
	"developer_comments": {
		"en-US": "Copies the current tab's URL and title as a Markdown/Jira/HTML link to the clipboard"
	},
	"homepage": {
		"en-US": "https://github.com/JayBeeDe/firefox_extensions/blob/main/caml/README.md"
	},
	"name": {
		"en-US": "Copy as Markdown Link"
	},
	"requires_payment": false,
	"slug": "copy-as-markdown-link",
	"summary": {
		"en-US": "Copies the current tab's URL and title as a Markdown/Jira/HTML link to the clipboard."
	},
	"support_email": {
		"en-US": "dev@delon.cloud"
	},
	"version": {
		"license": "GPL-3.0-only",
		"release_notes": {
			"en-US": "Fix icon issue and default keyboard shortcut improvement"
		}
	}
}